uhmbrella_api-0.1.3.dist-info/licenses/LICENSE
uhmbrella_api_sdk/__init__.py
uhmbrella_api_sdk/cli.py
uhmbrella_api-0.1.3.dist-info/METADATA
uhmbrella_api-0.1.3.dist-info/WHEEL
uhmbrella_api-0.1.3.dist-info/entry_points.txt
uhmbrella_api-0.1.3.dist-info/top_level.txt
uhmbrella_api-0.1.3.dist-info/RECORD
