Metadata-Version: 2.4
Name: uhmbrella-api
Version: 0.1.3
Summary: Uhmbrella AIMD - client SDK and CLI for the Uhmbrella AI music detection API.
Author-email: Uhmbrella <hello@uhmbrella.io>
Project-URL: Homepage, https://uhmbrella.io
Requires-Python: >=3.9
License-File: LICENSE
Requires-Dist: requests>=2.31.0
Requires-Dist: tqdm>=4.66.0
Dynamic: license-file
